elf_py_utils/__init__.py
elf_py_utils/CodeGen/CodeGen.py
elf_py_utils/CodeGen/EntityInfo.json
elf_py_utils/config_util.py
elf_py_utils/constants/__init__.py
elf_py_utils/constants/FormatConstant.py
elf_py_utils/elf_core.py
elf_py_utils/excel_util.py
elf_py_utils/kafka_util.py
elf_py_utils/logger_util.py
elf_py_utils/mqtt_util.py
elf_py_utils/mysql_util.py
elf_py_utils/redis_util.py
elf_py_utils/str_util.py
elf_py_utils/tcp_util.py
elf_py_utils/time_util.py
elf_py_utils/utils/__init__.py
elf_py_utils/utils/RedisClient.py
elf_py_utils-0.1.3.5.dist-info/METADATA
elf_py_utils-0.1.3.5.dist-info/WHEEL
elf_py_utils-0.1.3.5.dist-info/RECORD
