Metadata-Version: 2.1
Name: elf-py-utils
Version: 0.1.3.5
Summary: 
Author: TreeOfWord
Author-email: li_163jx@163.com
Requires-Python: >=3.8,<4.0
Classifier: Programming Language :: Python :: 3
Classifier: Programming Language :: Python :: 3.8
Classifier: Programming Language :: Python :: 3.9
Classifier: Programming Language :: Python :: 3.10
Classifier: Programming Language :: Python :: 3.11
Classifier: Programming Language :: Python :: 3.12
